lsf.py
lsf_lions_sectioned_format-2021.6.29.dist-info/LICENSE
lsf_lions_sectioned_format-2021.6.29.dist-info/METADATA
lsf_lions_sectioned_format-2021.6.29.dist-info/WHEEL
lsf_lions_sectioned_format-2021.6.29.dist-info/top_level.txt
lsf_lions_sectioned_format-2021.6.29.dist-info/RECORD
