Metadata-Version: 2.1
Name: lsf-lions-sectioned-format
Version: 2021.6.29
Summary: Read/write LSF plain-text container format files
Home-page: https://github.com/LionKimbro/lsf
Author: Lion Kimbro
Author-email: LionKimbro@gmail.com
License: UNKNOWN
Keywords: textfile,text,container,format
Platform: UNKNOWN
Classifier: Development Status :: 5 - Production/Stable
Classifier: Intended Audience :: Developers
Classifier: License :: CC0 1.0 Universal (CC0 1.0) Public Domain Dedication
Classifier: Programming Language :: Python :: 3
Classifier: Programming Language :: Python :: 3 :: Only
Classifier: Operating System :: OS Independent
Classifier: Topic :: Text Processing :: General
Requires-Python: >=3.6, <4
License-File: LICENSE
